squeeze_jrpc/__init__.py
squeeze_jrpc/commands.py
squeeze_jrpc/protocol/slim.py
squeeze_jrpc/queries.py
squeeze_jrpc-0.2.0.dist-info/METADATA
squeeze_jrpc-0.2.0.dist-info/WHEEL
squeeze_jrpc-0.2.0.dist-info/RECORD
