Metadata-Version: 2.1
Name: squeeze-jrpc
Version: 0.2.0
Summary: Wrapper for Logitech Media Server (aka SqueezeBox) JSON-RPC API
License: MIT
Author: Simon Redding
Author-email: s1m0n.r3dd1ng@gmail.com
Requires-Python: >=3.11,<4.0
Classifier: License :: OSI Approved :: MIT License
Classifier: Programming Language :: Python :: 3
Classifier: Programming Language :: Python :: 3.11
Classifier: Programming Language :: Python :: 3.12
Requires-Dist: requests (>=2.31.0,<3.0.0)
